odoo9_addon_website_snippet_anchor-9.0.1.0.0-py2.7-nspkg.pth
odoo_addons/website_snippet_anchor/__openerp__.py
odoo_addons/website_snippet_anchor/__init__.py
odoo_addons/website_snippet_anchor/README.rst
odoo_addons/website_snippet_anchor/i18n/it.po
odoo_addons/website_snippet_anchor/i18n/es.po
odoo_addons/website_snippet_anchor/i18n/ca.po
odoo_addons/website_snippet_anchor/i18n/sl.po
odoo_addons/website_snippet_anchor/i18n/nl.po
odoo_addons/website_snippet_anchor/i18n/de.po
odoo_addons/website_snippet_anchor/i18n/pt_BR.po
odoo_addons/website_snippet_anchor/i18n/el_GR.po
odoo_addons/website_snippet_anchor/views/snippets.xml
odoo_addons/website_snippet_anchor/views/assets.xml
odoo_addons/website_snippet_anchor/static/description/icon.png
odoo_addons/website_snippet_anchor/static/src/js/website_snippet_anchor.js
odoo_addons/website_snippet_anchor/static/src/xml/website_snippet_anchor.xml
odoo9_addon_website_snippet_anchor-9.0.1.0.0.dist-info/top_level.txt
odoo9_addon_website_snippet_anchor-9.0.1.0.0.dist-info/WHEEL
odoo9_addon_website_snippet_anchor-9.0.1.0.0.dist-info/RECORD
odoo9_addon_website_snippet_anchor-9.0.1.0.0.dist-info/metadata.json
odoo9_addon_website_snippet_anchor-9.0.1.0.0.dist-info/DESCRIPTION.rst
odoo9_addon_website_snippet_anchor-9.0.1.0.0.dist-info/METADATA
odoo9_addon_website_snippet_anchor-9.0.1.0.0.dist-info/namespace_packages.txt
